[
  {
    "id": 3100001,
    "m_accessory_id": 37010340,
    "enchantment_group_no": 70004041,
    "order": 1,
    "is_appraisal": 0
  },
  {
    "id": 3100002,
    "m_accessory_id": 38010340,
    "enchantment_group_no": 80004041,
    "order": 1,
    "is_appraisal": 0
  },
  {
    "id": 3100003,
    "m_accessory_id": 39010340,
    "enchantment_group_no": 90004041,
    "order": 1,
    "is_appraisal": 0
  },
  {
    "id": 3100004,
    "m_accessory_id": 37020340,
    "enchantment_group_no": 70004042,
    "order": 1,
    "is_appraisal": 0
  },
  {
    "id": 3100005,
    "m_accessory_id": 38020340,
    "enchantment_group_no": 80004042,
    "order": 1,
    "is_appraisal": 0
  },
  {
    "id": 3100006,
    "m_accessory_id": 39020340,
    "enchantment_group_no": 90004042,
    "order": 1,
    "is_appraisal": 0
  },
  {
    "id": 3100007,
    "m_accessory_id": 37010440,
    "enchantment_group_no": 70004041,
    "order": 1,
    "is_appraisal": 0
  },
  {
    "id": 3100008,
    "m_accessory_id": 38010440,
    "enchantment_group_no": 80004041,
    "order": 1,
    "is_appraisal": 0
  },
  {
    "id": 3100009,
    "m_accessory_id": 39010440,
    "enchantment_group_no": 90004041,
    "order": 1,
    "is_appraisal": 0
  },
  {
    "id": 3100010,
    "m_accessory_id": 37020440,
    "enchantment_group_no": 70004042,
    "order": 1,
    "is_appraisal": 0
  },
  {
    "id": 3100011,
    "m_accessory_id": 38020440,
    "enchantment_group_no": 80004042,
    "order": 1,
    "is_appraisal": 0
  },
  {
    "id": 3100012,
    "m_accessory_id": 39020440,
    "enchantment_group_no": 90004042,
    "order": 1,
    "is_appraisal": 0
  },
  {
    "id": 3100013,
    "m_accessory_id": 37010540,
    "enchantment_group_no": 70004041,
    "order": 1,
    "is_appraisal": 0
  },
  {
    "id": 3100014,
    "m_accessory_id": 38010540,
    "enchantment_group_no": 80004041,
    "order": 1,
    "is_appraisal": 0
  },
  {
    "id": 3100015,
    "m_accessory_id": 39010540,
    "enchantment_group_no": 90004041,
    "order": 1,
    "is_appraisal": 0
  },
  {
    "id": 3100016,
    "m_accessory_id": 37020540,
    "enchantment_group_no": 70004042,
    "order": 1,
    "is_appraisal": 0
  },
  {
    "id": 3100017,
    "m_accessory_id": 38020540,
    "enchantment_group_no": 80004042,
    "order": 1,
    "is_appraisal": 0
  },
  {
    "id": 3100018,
    "m_accessory_id": 39020540,
    "enchantment_group_no": 90004042,
    "order": 1,
    "is_appraisal": 0
  }
]