[
  {
    "id": 1,
    "asset_id": "2022201",
    "group_no": 18,
    "item_no": 1,
    "priority_order": 1,
    "title": "氷河の厄災",
    "desciption": "属性は水。氷雪、氷河期にまつわる災禍を\n具現化した厄災。氷雪の階層に生息し、\n雪の中の地中を移動する。\n大穴内の階層に出現した時から、\n大穴の周辺や前線基地に至るまで\n異常気象を発生させ、季節外れの大雪や、\n氷の世界をもたらす。",
    "release_at": "2026-06-11 00:00:00",
    "display_order": 1,
    "size": 5,
    "quest_type": 2,
    "quest_id": 1020406
  },
  {
    "id": 2,
    "asset_id": "2026501",
    "group_no": 18,
    "item_no": 2,
    "priority_order": 1,
    "title": "飢餓の厄災",
    "desciption": "属性は闇。飢えと枯れにまつわる災禍を\n具現化した厄災。周囲の植物を枯らし、\n生物を飢えさせて死に至らしめ、\n凶作と飢餓をもたらす。\n大穴出現直後に最初に出現した厄災であり\n連合調査隊及び、大穴周辺に甚大な被害を\n与えた。三大国の協力によって\n一度は退けることに成功するも、\n大穴内のある階層で力を蓄えた後、\n幾度も人類の前にその脅威をもたらす。",
    "release_at": "2026-06-11 00:00:00",
    "display_order": 2,
    "size": 5,
    "quest_type": 2,
    "quest_id": 1040505
  },
  {
    "id": 3,
    "asset_id": "2024401",
    "group_no": 18,
    "item_no": 3,
    "priority_order": 1,
    "title": "天使の厄災",
    "desciption": "属性は光。大いなる力への信仰によって\nもたらされる災禍を具現化した厄災。\n絶望に苦しむ死者の魂を救済するという\n名目で現れ、彼らを天へと召す存在。\nしかし、その行為は救済ではなく、\nすべてを滅ぼすこと。\n天使の厄災が降り立った大地は、\n生命の痕跡が一切ない虚無の世界と化す。",
    "release_at": "2026-06-11 00:00:00",
    "display_order": 3,
    "size": 5,
    "quest_type": 2,
    "quest_id": 1060505
  },
  {
    "id": 10000,
    "asset_id": "2001101",
    "group_no": 1,
    "item_no": 4,
    "priority_order": 1,
    "title": "ファイヤーゴブリン",
    "desciption": "火炎の矢を放つ小鬼。\nその獰猛な眼差しは、\n獲物を焼き尽くす炎のように燃えている。",
    "release_at": "2026-06-11 00:00:00",
    "display_order": 1,
    "size": 1,
    "quest_type": 2,
    "quest_id": 1030503
  },
  {
    "id": 10001,
    "asset_id": "2001201",
    "group_no": 1,
    "item_no": 5,
    "priority_order": 1,
    "title": "アイスゴブリン",
    "desciption": "氷結の矢を放つ小鬼。\nその冷酷な笑みは、\n獲物を凍てつかせる氷のように冷たい。",
    "release_at": "2026-06-11 00:00:00",
    "display_order": 2,
    "size": 1,
    "quest_type": 2,
    "quest_id": 1020406
  },
  {
    "id": 10002,
    "asset_id": "2001301",
    "group_no": 1,
    "item_no": 6,
    "priority_order": 1,
    "title": "マッドゴブリン",
    "desciption": "岩石の矢を放つ小鬼。\nその屈強な腕力は、\n獲物を貫く岩のように硬い。",
    "release_at": "2026-06-11 00:00:00",
    "display_order": 3,
    "size": 1,
    "quest_type": 2,
    "quest_id": 1010306
  },
  {
    "id": 10003,
    "asset_id": "2001401",
    "group_no": 1,
    "item_no": 7,
    "priority_order": 1,
    "title": "エレキゴブリン",
    "desciption": "光輝の矢を放つ小鬼。\nその狡猾な策略は、\n獲物を欺く光のように眩しい。",
    "release_at": "2026-06-11 00:00:00",
    "display_order": 4,
    "size": 1,
    "quest_type": 2,
    "quest_id": 1060505
  },
  {
    "id": 10004,
    "asset_id": "2001501",
    "group_no": 1,
    "item_no": 8,
    "priority_order": 1,
    "title": "ダークゴブリン",
    "desciption": "呪詛の矢を放つ小鬼。\nその邪悪な影は、\n獲物を蝕む闇のように深い。",
    "release_at": "2026-06-11 00:00:00",
    "display_order": 5,
    "size": 1,
    "quest_type": 2,
    "quest_id": 1040505
  },
  {
    "id": 10005,
    "asset_id": "2001001",
    "group_no": 1,
    "item_no": 9,
    "priority_order": 1,
    "title": "メタルゴブリン",
    "desciption": "鋼鉄の矢を放つ小鬼。\nその鍛えられた頑強な皮膚は、\nあらゆる攻撃を弾き返す。",
    "release_at": "2026-06-11 00:00:00",
    "display_order": 6,
    "size": 1,
    "quest_type": 2,
    "quest_id": 1050503
  },
  {
    "id": 10100,
    "asset_id": "2002101",
    "group_no": 2,
    "item_no": 10,
    "priority_order": 1,
    "title": "ファイヤードワーフ",
    "desciption": "赤熱のハンマーを振るうドワーフ。\n性格は炎のように熱く、\nその一撃は大地を焼き尽くす。",
    "release_at": "2026-06-11 00:00:00",
    "display_order": 1,
    "size": 1,
    "quest_type": 2,
    "quest_id": 1030503
  },
  {
    "id": 10101,
    "asset_id": "2002201",
    "group_no": 2,
    "item_no": 11,
    "priority_order": 1,
    "title": "アイスドワーフ",
    "desciption": "氷雪のハンマーを振るうドワーフ。\n性格は氷のように冷たく、\nその一撃はすべてを凍てつかせる。",
    "release_at": "2026-06-11 00:00:00",
    "display_order": 2,
    "size": 1,
    "quest_type": 2,
    "quest_id": 1020406
  },
  {
    "id": 10102,
    "asset_id": "2002301",
    "group_no": 2,
    "item_no": 12,
    "priority_order": 1,
    "title": "ロックドワーフ",
    "desciption": "岩盤のハンマーを振るうドワーフ。\n性格は岩のように頑固、\nその一撃は大地を粉砕する。",
    "release_at": "2026-06-11 00:00:00",
    "display_order": 3,
    "size": 1,
    "quest_type": 2,
    "quest_id": 1010306
  },
  {
    "id": 10103,
    "asset_id": "2002401",
    "group_no": 2,
    "item_no": 13,
    "priority_order": 1,
    "title": "ホーリードワーフ",
    "desciption": "聖なるハンマーを振るうドワーフ。\n性格は光のように慈悲深く、\nその一撃は邪悪を打ち払う。",
    "release_at": "2026-06-11 00:00:00",
    "display_order": 4,
    "size": 1,
    "quest_type": 2,
    "quest_id": 1060505
  },
  {
    "id": 10104,
    "asset_id": "2002501",
    "group_no": 2,
    "item_no": 14,
    "priority_order": 1,
    "title": "シャドウドワーフ",
    "desciption": "深淵のハンマーを振るうドワーフ。\n性格は闇のように閉鎖的で、\nその一撃は魂を蝕む。",
    "release_at": "2026-06-11 00:00:00",
    "display_order": 5,
    "size": 1,
    "quest_type": 2,
    "quest_id": 1040505
  },
  {
    "id": 10105,
    "asset_id": "2002001",
    "group_no": 2,
    "item_no": 15,
    "priority_order": 1,
    "title": "アイアンドワーフ",
    "desciption": "鋼鉄のハンマーを振るうドワーフ。\n性格は鋼鉄のように冷徹で、\nその一撃はすべて叩きのめす。",
    "release_at": "2026-06-11 00:00:00",
    "display_order": 6,
    "size": 1,
    "quest_type": 2,
    "quest_id": 1050503
  },
  {
    "id": 10200,
    "asset_id": "2003101",
    "group_no": 3,
    "item_no": 16,
    "priority_order": 1,
    "title": "炎の魔導士",
    "desciption": "紅蓮の魔導書を操る魔道士。\nその瞳に宿るは、生命を燃え上がらせる情熱。\n陽だまりのような温かさで傷を癒やす。",
    "release_at": "2026-06-11 00:00:00",
    "display_order": 1,
    "size": 1,
    "quest_type": 2,
    "quest_id": 1030503
  },
  {
    "id": 10201,
    "asset_id": "2003201",
    "group_no": 3,
    "item_no": 17,
    "priority_order": 1,
    "title": "水の魔導士",
    "desciption": "深海の魔導書を操る魔道士。\nその瞳に宿るは、生命を潤いで満たす清涼。\n湧き水のような清らかさで傷を癒やす。",
    "release_at": "2026-06-11 00:00:00",
    "display_order": 2,
    "size": 1,
    "quest_type": 2,
    "quest_id": 1020406
  },
  {
    "id": 10202,
    "asset_id": "2003301",
    "group_no": 3,
    "item_no": 18,
    "priority_order": 1,
    "title": "地の魔導士",
    "desciption": "豊穣の魔導書を操る魔道士。\nその瞳に宿るは、生命を育む森羅万象。\n新緑のように生命力を蘇らせる。",
    "release_at": "2026-06-11 00:00:00",
    "display_order": 3,
    "size": 1,
    "quest_type": 2,
    "quest_id": 1010306
  },
  {
    "id": 10203,
    "asset_id": "2003401",
    "group_no": 3,
    "item_no": 19,
    "priority_order": 1,
    "title": "光の魔導士",
    "desciption": "天空の魔導書を操る魔道士。\nその瞳に宿るは、全てを浄化する聖光。\n陽光のような輝きで傷を癒やす。",
    "release_at": "2026-06-11 00:00:00",
    "display_order": 4,
    "size": 1,
    "quest_type": 2,
    "quest_id": 1060505
  },
  {
    "id": 10204,
    "asset_id": "2003501",
    "group_no": 3,
    "item_no": 20,
    "priority_order": 1,
    "title": "闇の魔導士",
    "desciption": "混沌の魔導書を操る魔道士。\nその瞳に宿るは、全てを蝕む暗黒。\n月明かりのような静けさで傷を癒やす。",
    "release_at": "2026-06-11 00:00:00",
    "display_order": 5,
    "size": 1,
    "quest_type": 2,
    "quest_id": 1040505
  },
  {
    "id": 10205,
    "asset_id": "2003001",
    "group_no": 3,
    "item_no": 21,
    "priority_order": 1,
    "title": "古の魔導士",
    "desciption": "古代の魔導書を操る魔道士。\nその瞳に宿るは、失われた古代の叡智。\n万象を原初の状態へと蘇らせる。",
    "release_at": "2026-06-11 00:00:00",
    "display_order": 6,
    "size": 1,
    "quest_type": 2,
    "quest_id": 1050503
  },
  {
    "id": 10300,
    "asset_id": "2004101",
    "group_no": 4,
    "item_no": 22,
    "priority_order": 1,
    "title": "炎纏う魔族の女魔法使い",
    "desciption": "業火を操る魔族の女魔法使い。\nその炎は、地獄の業火を思わせる。\n敵を焼き尽くすまで、彼女の攻撃は止まらない。",
    "release_at": "2026-06-11 00:00:00",
    "display_order": 1,
    "size": 1,
    "quest_type": 2,
    "quest_id": 1030503
  },
  {
    "id": 10301,
    "asset_id": "2004201",
    "group_no": 4,
    "item_no": 23,
    "priority_order": 1,
    "title": "水纏う魔族の女魔法使い",
    "desciption": "氷結の魔法を操る魔族の女魔法使い。\nその冷気は、すべてを凍てつかせる。\n彼女の杖は、戦場を氷漬けにする。",
    "release_at": "2026-06-11 00:00:00",
    "display_order": 2,
    "size": 1,
    "quest_type": 2,
    "quest_id": 1020406
  },
  {
    "id": 10302,
    "asset_id": "2004301",
    "group_no": 4,
    "item_no": 24,
    "priority_order": 1,
    "title": "土纏う魔族の女魔法使い",
    "desciption": "土の精霊と契約した魔族の女魔法使い。\nその力は大地を揺るがす。\n彼女の杖は、戦場を混乱に陥れる。",
    "release_at": "2026-06-11 00:00:00",
    "display_order": 3,
    "size": 1,
    "quest_type": 2,
    "quest_id": 1010306
  },
  {
    "id": 10303,
    "asset_id": "2004401",
    "group_no": 4,
    "item_no": 25,
    "priority_order": 1,
    "title": "光纏う魔族の女魔法使い",
    "desciption": "光を操る魔族の女魔法使い。\nその魔法は雷撃を生み、敵を撃ち焦がす。\n彼女の杖は、戦場を焦土と化す。",
    "release_at": "2026-06-11 00:00:00",
    "display_order": 4,
    "size": 1,
    "quest_type": 2,
    "quest_id": 1060505
  },
  {
    "id": 10304,
    "asset_id": "2004501",
    "group_no": 4,
    "item_no": 26,
    "priority_order": 1,
    "title": "闇纏う魔族の女魔法使い",
    "desciption": "闇を操る魔族の女魔法使い。\nその魔法は、敵を恐怖に陥れる。\n敵を闇に葬るまで、彼女の攻撃は止まらない。",
    "release_at": "2026-06-11 00:00:00",
    "display_order": 5,
    "size": 1,
    "quest_type": 2,
    "quest_id": 1040505
  },
  {
    "id": 10305,
    "asset_id": "2004001",
    "group_no": 4,
    "item_no": 27,
    "priority_order": 1,
    "title": "天翔ける魔族の女魔法使い",
    "desciption": "空を駆ける女魔法使い。\nその魔法は、風を呼び、嵐を巻き起こす。\n彼女の杖は、天空を支配する。",
    "release_at": "2026-06-11 00:00:00",
    "display_order": 6,
    "size": 1,
    "quest_type": 2,
    "quest_id": 1050503
  },
  {
    "id": 10400,
    "asset_id": "2005101",
    "group_no": 5,
    "item_no": 28,
    "priority_order": 1,
    "title": "フレイムウルフ",
    "desciption": "灼熱の炎を纏いし獣。\n俊敏な動きで獲物に近付き、\n鋭い牙で骨を砕く。",
    "release_at": "2026-06-11 00:00:00",
    "display_order": 1,
    "size": 1,
    "quest_type": 2,
    "quest_id": 1030503
  },
  {
    "id": 10401,
    "asset_id": "2005201",
    "group_no": 5,
    "item_no": 29,
    "priority_order": 1,
    "title": "ブリザードウルフ",
    "desciption": "氷の毛皮を纏いし獣。\n俊敏な動きで獲物に近付き、\n冷たい牙でその血を凍らせる。",
    "release_at": "2026-06-11 00:00:00",
    "display_order": 2,
    "size": 1,
    "quest_type": 2,
    "quest_id": 1020406
  },
  {
    "id": 10402,
    "asset_id": "2005301",
    "group_no": 5,
    "item_no": 30,
    "priority_order": 1,
    "title": "アースウルフ",
    "desciption": "大地の力を宿した森の捕食者。\nその咆哮は大地を揺るがし、\n鋭い牙で骨を砕く。",
    "release_at": "2026-06-11 00:00:00",
    "display_order": 3,
    "size": 1,
    "quest_type": 2,
    "quest_id": 1010306
  },
  {
    "id": 10403,
    "asset_id": "2005401",
    "group_no": 5,
    "item_no": 31,
    "priority_order": 1,
    "title": "シャイニーウルフ",
    "desciption": "聖なる光を纏いし獣。\nその毛皮は黄金に輝き、\n鋭い牙で骨を砕く。",
    "release_at": "2026-06-11 00:00:00",
    "display_order": 4,
    "size": 1,
    "quest_type": 2,
    "quest_id": 1060505
  },
  {
    "id": 10404,
    "asset_id": "2005501",
    "group_no": 5,
    "item_no": 32,
    "priority_order": 1,
    "title": "ダークウルフ",
    "desciption": "闇の炎を纏いし獣。\n俊敏な動きで獲物に近付き、\n鋭い牙で骨を砕く。",
    "release_at": "2026-06-11 00:00:00",
    "display_order": 5,
    "size": 1,
    "quest_type": 2,
    "quest_id": 1040505
  },
  {
    "id": 10405,
    "asset_id": "2005001",
    "group_no": 5,
    "item_no": 33,
    "priority_order": 1,
    "title": "メタルウルフ",
    "desciption": "異世界の技術で製造された鉄の獣。\nその動力源は謎だが、機動性に優れ、\n固く鋭い牙で侵入者を襲う。",
    "release_at": "2026-06-11 00:00:00",
    "display_order": 6,
    "size": 1,
    "quest_type": 2,
    "quest_id": 1050503
  },
  {
    "id": 10500,
    "asset_id": "2006101",
    "group_no": 6,
    "item_no": 34,
    "priority_order": 1,
    "title": "フレアゴーレム",
    "desciption": "紅蓮の魔石を動力源とする炎の人造人間。\n両腕から繰り出される灼熱の拳は、\nすべてを灰燼と化す。",
    "release_at": "2026-06-11 00:00:00",
    "display_order": 1,
    "size": 2,
    "quest_type": 2,
    "quest_id": 1030503
  },
  {
    "id": 10501,
    "asset_id": "2006201",
    "group_no": 6,
    "item_no": 35,
    "priority_order": 1,
    "title": "アイスゴーレム",
    "desciption": "深海の魔石を動力源とする氷の人造人間。\n両腕から繰り出される絶対零度の拳は、\nすべてを凍結させる。",
    "release_at": "2026-06-11 00:00:00",
    "display_order": 2,
    "size": 2,
    "quest_type": 2,
    "quest_id": 1020406
  },
  {
    "id": 10502,
    "asset_id": "2006301",
    "group_no": 6,
    "item_no": 36,
    "priority_order": 1,
    "title": "ウッドゴーレム",
    "desciption": "大地の魔石を動力源とする岩の人造人間。\n両腕から繰り出される粉砕の拳は、\nすべてを瓦礫と化す。",
    "release_at": "2026-06-11 00:00:00",
    "display_order": 3,
    "size": 2,
    "quest_type": 2,
    "quest_id": 1010306
  },
  {
    "id": 10503,
    "asset_id": "2006401",
    "group_no": 6,
    "item_no": 37,
    "priority_order": 1,
    "title": "スターゴーレム",
    "desciption": "聖なる魔石を動力源とする光の人造人間。\n両腕から繰り出される裁きの拳は、\nすべてを浄化する。",
    "release_at": "2026-06-11 00:00:00",
    "display_order": 4,
    "size": 2,
    "quest_type": 2,
    "quest_id": 1060505
  },
  {
    "id": 10504,
    "asset_id": "2006501",
    "group_no": 6,
    "item_no": 38,
    "priority_order": 1,
    "title": "ダークゴーレム",
    "desciption": "深淵の魔石を動力源とする闇の人造人間。\n両腕から繰り出される終焉の拳は、\nすべてを消滅させる。",
    "release_at": "2026-06-11 00:00:00",
    "display_order": 5,
    "size": 2,
    "quest_type": 2,
    "quest_id": 1040505
  },
  {
    "id": 10505,
    "asset_id": "2006001",
    "group_no": 6,
    "item_no": 39,
    "priority_order": 1,
    "title": "メタルゴーレム",
    "desciption": "異世界の技術で造られた鉄の人造人間。\n両腕から繰り出される鉄拳は、すべてを押しつぶす。\nその姿は、まるで意志を持つ鋼鉄の鎧。",
    "release_at": "2026-06-11 00:00:00",
    "display_order": 6,
    "size": 2,
    "quest_type": 2,
    "quest_id": 1050503
  },
  {
    "id": 10600,
    "asset_id": "2007101",
    "group_no": 7,
    "item_no": 40,
    "priority_order": 1,
    "title": "マグマスライム",
    "desciption": "灼熱の液体を吐き出す粘液状のモンスター。\nその体液に触れた者は大火傷を負う。\n油断すれば一瞬で丸焦げにされるだろう。",
    "release_at": "2026-06-11 00:00:00",
    "display_order": 1,
    "size": 2,
    "quest_type": 2,
    "quest_id": 1030503
  },
  {
    "id": 10601,
    "asset_id": "2007201",
    "group_no": 7,
    "item_no": 41,
    "priority_order": 1,
    "title": "アクアスライム",
    "desciption": "冷気を帯びた液体を吐き出す粘液状のモンスター。\nその体液に触れた者は凍傷を負う。\n油断すれば一瞬で凍り漬けにされるだろう。",
    "release_at": "2026-06-11 00:00:00",
    "display_order": 2,
    "size": 2,
    "quest_type": 2,
    "quest_id": 1020406
  },
  {
    "id": 10602,
    "asset_id": "2007301",
    "group_no": 7,
    "item_no": 42,
    "priority_order": 1,
    "title": "マッドスライム",
    "desciption": "泥状の液体を吐き出す粘液状のモンスター。\nその体液に触れた者は泥まみれになり、動きが鈍くなる。\n油断すれば一瞬で泥濘に沈められるだろう。",
    "release_at": "2026-06-11 00:00:00",
    "display_order": 3,
    "size": 2,
    "quest_type": 2,
    "quest_id": 1010306
  },
  {
    "id": 10603,
    "asset_id": "2007401",
    "group_no": 7,
    "item_no": 43,
    "priority_order": 1,
    "title": "エレキスライム",
    "desciption": "光り輝く液体を吐き出す粘液状のモンスター。\nその体液に触れた者は電撃が走り、痺れ状態になる。\n油断すれば一瞬で命を落とすことになるだろう。",
    "release_at": "2026-06-11 00:00:00",
    "display_order": 4,
    "size": 2,
    "quest_type": 2,
    "quest_id": 1060505
  },
  {
    "id": 10604,
    "asset_id": "2007501",
    "group_no": 7,
    "item_no": 44,
    "priority_order": 1,
    "title": "ポイズンスライム",
    "desciption": "毒液を吐き出す粘液状のモンスター。\nその体液に触れた者は毒に侵され、衰弱していく。\n油断すれば手遅れになるだろう。",
    "release_at": "2026-06-11 00:00:00",
    "display_order": 5,
    "size": 2,
    "quest_type": 2,
    "quest_id": 1040505
  },
  {
    "id": 10605,
    "asset_id": "2007001",
    "group_no": 7,
    "item_no": 45,
    "priority_order": 1,
    "title": "アイアンスライム",
    "desciption": "変幻自在の金属生命体。\nその体液は、あらゆる金属を腐食させる。\n油断すれば武器が溶けてしまうだろう。",
    "release_at": "2026-06-11 00:00:00",
    "display_order": 6,
    "size": 2,
    "quest_type": 2,
    "quest_id": 1050503
  },
  {
    "id": 10700,
    "asset_id": "2008101",
    "group_no": 8,
    "item_no": 46,
    "priority_order": 1,
    "title": "フレイムハーピィ",
    "desciption": "炎の翼を持つ女面鳥身のモンスター。\n彼女らの歌声は獲物を誘い、\n鋭い鉤爪で肉を切り裂き、血を啜る。",
    "release_at": "2026-06-11 00:00:00",
    "display_order": 1,
    "size": 1,
    "quest_type": 2,
    "quest_id": 1030503
  },
  {
    "id": 10701,
    "asset_id": "2008201",
    "group_no": 8,
    "item_no": 47,
    "priority_order": 1,
    "title": "アクアハーピィ",
    "desciption": "氷の翼を持つ女面鳥身のモンスター。\n彼女らの歌声は獲物を誘い、\n鋭い鉤爪で肉を切り裂き、血を啜る。",
    "release_at": "2026-06-11 00:00:00",
    "display_order": 2,
    "size": 1,
    "quest_type": 2,
    "quest_id": 1020406
  },
  {
    "id": 10702,
    "asset_id": "2008301",
    "group_no": 8,
    "item_no": 48,
    "priority_order": 1,
    "title": "グラスハーピィ",
    "desciption": "森の精霊と一体化した女面鳥身のモンスター。\n彼女らの歌声は獲物を誘い、\n鋭い鉤爪で肉を切り裂き、血を啜る。",
    "release_at": "2026-06-11 00:00:00",
    "display_order": 3,
    "size": 1,
    "quest_type": 2,
    "quest_id": 1010306
  },
  {
    "id": 10703,
    "asset_id": "2008401",
    "group_no": 8,
    "item_no": 49,
    "priority_order": 1,
    "title": "エレキハーピィ",
    "desciption": "激しい雷を操る女面鳥身のモンスター。\n彼女らの歌声は獲物を誘い、\n鋭い鉤爪で肉を切り裂き、血を啜る。",
    "release_at": "2026-06-11 00:00:00",
    "display_order": 4,
    "size": 1,
    "quest_type": 2,
    "quest_id": 1060505
  },
  {
    "id": 10704,
    "asset_id": "2008501",
    "group_no": 8,
    "item_no": 50,
    "priority_order": 1,
    "title": "エレキハーピィ",
    "desciption": "闇の眷属である女面鳥身のモンスター。\n彼女らの歌声は獲物を誘い、\n鋭い鉤爪で肉を切り裂き、血を啜る。",
    "release_at": "2026-06-11 00:00:00",
    "display_order": 5,
    "size": 1,
    "quest_type": 2,
    "quest_id": 1040505
  },
  {
    "id": 10705,
    "asset_id": "2008001",
    "group_no": 8,
    "item_no": 51,
    "priority_order": 1,
    "title": "メタルハーピィ",
    "desciption": "鉄の翼を持つ女面鳥身のモンスター。\n彼女らの歌声は獲物を誘い、\n鋭い鉤爪で肉を切り裂き、血を啜る。",
    "release_at": "2026-06-11 00:00:00",
    "display_order": 6,
    "size": 1,
    "quest_type": 2,
    "quest_id": 1050503
  },
  {
    "id": 10800,
    "asset_id": "2009101",
    "group_no": 9,
    "item_no": 52,
    "priority_order": 1,
    "title": "炎の剣士",
    "desciption": "灼熱の刃を振るう女剣士。\nその剣技は、炎の如く荒々しい。\n大穴の発見物を巡る戦いは、避けられない運命となる。",
    "release_at": "2026-06-11 00:00:00",
    "display_order": 1,
    "size": 1,
    "quest_type": 2,
    "quest_id": 1030503
  },
  {
    "id": 10801,
    "asset_id": "2009201",
    "group_no": 9,
    "item_no": 53,
    "priority_order": 1,
    "title": "水の剣士",
    "desciption": "氷の刃を振るう女剣士。\nその剣技は、しなやかで冷酷。\n大穴の発見物を巡る戦いは、避けられない運命となる。",
    "release_at": "2026-06-11 00:00:00",
    "display_order": 2,
    "size": 1,
    "quest_type": 2,
    "quest_id": 1020406
  },
  {
    "id": 10802,
    "asset_id": "2009301",
    "group_no": 9,
    "item_no": 54,
    "priority_order": 1,
    "title": "地の剣士",
    "desciption": "大地の力を纏った女戦士。\nその一撃は、岩をも砕く。\n大穴の発見物を巡る戦いは、避けられない運命となる。",
    "release_at": "2026-06-11 00:00:00",
    "display_order": 3,
    "size": 1,
    "quest_type": 2,
    "quest_id": 1010306
  },
  {
    "id": 10803,
    "asset_id": "2009401",
    "group_no": 9,
    "item_no": 55,
    "priority_order": 1,
    "title": "光の剣士",
    "desciption": "神に仕えし女戦士。\nだが、その心は、狂信に染まっている。\n彼女は神の名の下に、主人公たちに牙を剥く。",
    "release_at": "2026-06-11 00:00:00",
    "display_order": 4,
    "size": 1,
    "quest_type": 2,
    "quest_id": 1060505
  },
  {
    "id": 10804,
    "asset_id": "2009501",
    "group_no": 9,
    "item_no": 56,
    "priority_order": 1,
    "title": "闇の剣士",
    "desciption": "邪悪な力に魅入られた女戦士。\nその心は、憎悪と復讐に燃えている。\n大穴の発見物を巡る戦いにおいて、彼女は闇の復讐者となる。",
    "release_at": "2026-06-11 00:00:00",
    "display_order": 5,
    "size": 1,
    "quest_type": 2,
    "quest_id": 1040505
  },
  {
    "id": 10805,
    "asset_id": "2009001",
    "group_no": 9,
    "item_no": 57,
    "priority_order": 1,
    "title": "鋼の剣士",
    "desciption": "熟練の技を誇る女剣士。\nその剣技は、あらゆる状況に対応できる。\n大穴の発見物を巡る戦いは、避けられない運命となる。",
    "release_at": "2026-06-11 00:00:00",
    "display_order": 6,
    "size": 1,
    "quest_type": 2,
    "quest_id": 1050503
  },
  {
    "id": 10806,
    "asset_id": "2010101",
    "group_no": 9,
    "item_no": 58,
    "priority_order": 1,
    "title": "炎の騎士",
    "desciption": "灼熱の炎を纏いし守護者。\nその刃は、相手を焼き尽くす。\n兜の下に隠された顔は、怒りの炎に満ちている。",
    "release_at": "2026-06-11 00:00:00",
    "display_order": 7,
    "size": 1,
    "quest_type": 2,
    "quest_id": 1030503
  },
  {
    "id": 10807,
    "asset_id": "2010201",
    "group_no": 9,
    "item_no": 59,
    "priority_order": 1,
    "title": "水の騎士",
    "desciption": "氷の刃を振るう守護者。\nその剣技は、水のようにしなやかで、そして冷酷。\n兜の下に隠された表情は、常に冷静。",
    "release_at": "2026-06-11 00:00:00",
    "display_order": 8,
    "size": 1,
    "quest_type": 2,
    "quest_id": 1020406
  },
  {
    "id": 10808,
    "asset_id": "2010301",
    "group_no": 9,
    "item_no": 60,
    "priority_order": 1,
    "title": "地の騎士",
    "desciption": "大地の力を纏いし守護者。\nその片手剣は、岩をも砕く。\n兜の下に隠された素顔は、決して揺るがない。",
    "release_at": "2026-06-11 00:00:00",
    "display_order": 9,
    "size": 1,
    "quest_type": 2,
    "quest_id": 1010306
  },
  {
    "id": 10809,
    "asset_id": "2010401",
    "group_no": 9,
    "item_no": 61,
    "priority_order": 1,
    "title": "光の騎士",
    "desciption": "神々の使者たる守護者。\nその刃は、神の裁きを執行する。\n兜の下に隠された顔は、狂信に染まっている。",
    "release_at": "2026-06-11 00:00:00",
    "display_order": 10,
    "size": 1,
    "quest_type": 2,
    "quest_id": 1060505
  },
  {
    "id": 10810,
    "asset_id": "2010501",
    "group_no": 9,
    "item_no": 62,
    "priority_order": 1,
    "title": "闇の騎士",
    "desciption": "邪悪な力に魅入られた守護者。\nその心は、憎悪と復讐に燃えている。\n兜の下には、底知れぬ闇が渦巻いている。",
    "release_at": "2026-06-11 00:00:00",
    "display_order": 11,
    "size": 1,
    "quest_type": 2,
    "quest_id": 1040505
  },
  {
    "id": 10811,
    "asset_id": "2010001",
    "group_no": 9,
    "item_no": 63,
    "priority_order": 1,
    "title": "鋼の騎士",
    "desciption": "流浪の守護者。\nその剣技は、あらゆる状況に対応できる。\n兜の下に隠された素顔を知る者はいない。",
    "release_at": "2026-06-11 00:00:00",
    "display_order": 12,
    "size": 1,
    "quest_type": 2,
    "quest_id": 1050503
  },
  {
    "id": 10812,
    "asset_id": "2011101",
    "group_no": 9,
    "item_no": 64,
    "priority_order": 1,
    "title": "炎の魔法使い",
    "desciption": "炎を操る魔法使い。\nその杖は、灼熱の弾丸を放つ。\n戦場を焼き尽くすまで、彼の攻撃は止まらない。",
    "release_at": "2026-06-11 00:00:00",
    "display_order": 13,
    "size": 1,
    "quest_type": 2,
    "quest_id": 1030503
  },
  {
    "id": 10813,
    "asset_id": "2011201",
    "group_no": 9,
    "item_no": 65,
    "priority_order": 1,
    "title": "水の魔法使い",
    "desciption": "氷結の魔法を操る魔法使い。\nその杖は、氷の矢を放ち、敵を凍てつかせる。\n戦場を氷漬けにするまで、彼の攻撃は止まらない。",
    "release_at": "2026-06-11 00:00:00",
    "display_order": 14,
    "size": 1,
    "quest_type": 2,
    "quest_id": 1020406
  },
  {
    "id": 10814,
    "asset_id": "2011301",
    "group_no": 9,
    "item_no": 66,
    "priority_order": 1,
    "title": "地の魔法使い",
    "desciption": "大地を操る魔法使い。\nその杖は、岩の弾丸を放ち、敵を粉砕する。\n戦場を瓦礫の山に変えるまで、彼の攻撃は止まらない。",
    "release_at": "2026-06-11 00:00:00",
    "display_order": 15,
    "size": 1,
    "quest_type": 2,
    "quest_id": 1010306
  },
  {
    "id": 10815,
    "asset_id": "2011401",
    "group_no": 9,
    "item_no": 67,
    "priority_order": 1,
    "title": "光の魔法使い",
    "desciption": "光を操る魔法使い。\nその杖は、光の矢を放ち、敵を撃ち抜く。\n戦場を焦土と化すまで、彼の攻撃は止まらない。",
    "release_at": "2026-06-11 00:00:00",
    "display_order": 16,
    "size": 1,
    "quest_type": 2,
    "quest_id": 1060505
  },
  {
    "id": 10816,
    "asset_id": "2011501",
    "group_no": 9,
    "item_no": 68,
    "priority_order": 1,
    "title": "闇の魔法使い",
    "desciption": "闇を操る魔法使い。\nその力は、敵を恐怖に陥れる。\n戦場を闇で包み込むまで、彼の攻撃は止まらない。",
    "release_at": "2026-06-11 00:00:00",
    "display_order": 17,
    "size": 1,
    "quest_type": 2,
    "quest_id": 1040505
  },
  {
    "id": 10817,
    "asset_id": "2011001",
    "group_no": 9,
    "item_no": 69,
    "priority_order": 1,
    "title": "空の魔法使い",
    "desciption": "空を操る魔法使い。\nその杖は、風の弾丸を放ち、敵を吹き飛ばす。\n彼の攻撃は戦場を混乱に陥れる。",
    "release_at": "2026-06-11 00:00:00",
    "display_order": 18,
    "size": 1,
    "quest_type": 2,
    "quest_id": 1050503
  },
  {
    "id": 10818,
    "asset_id": "2012101",
    "group_no": 9,
    "item_no": 70,
    "priority_order": 1,
    "title": "炎の弓使い",
    "desciption": "火の精霊と契約したエルフの弓使い。\nその矢は、灼熱の炎を纏い敵を焼き尽くす。\n森の守護者として、侵入者を決して許さない。",
    "release_at": "2026-06-11 00:00:00",
    "display_order": 19,
    "size": 1,
    "quest_type": 2,
    "quest_id": 1030503
  },
  {
    "id": 10819,
    "asset_id": "2012201",
    "group_no": 9,
    "item_no": 71,
    "priority_order": 1,
    "title": "水の弓使い",
    "desciption": "水の精霊と契約したエルフの弓使い。\nその矢は、凍てつく冷気を纏い敵を凍結させる。\n森の守護者として、侵入者を決して許さない。",
    "release_at": "2026-06-11 00:00:00",
    "display_order": 20,
    "size": 1,
    "quest_type": 2,
    "quest_id": 1020406
  },
  {
    "id": 10820,
    "asset_id": "2012301",
    "group_no": 9,
    "item_no": 72,
    "priority_order": 1,
    "title": "地の弓使い",
    "desciption": "大地の精霊と契約したエルフの弓使い。\nその矢は、大地の力を凝縮した岩の矢となり敵を粉砕する。\n森の守護者として、侵入者を決して許さない。",
    "release_at": "2026-06-11 00:00:00",
    "display_order": 21,
    "size": 1,
    "quest_type": 2,
    "quest_id": 1010306
  },
  {
    "id": 10821,
    "asset_id": "2012401",
    "group_no": 9,
    "item_no": 73,
    "priority_order": 1,
    "title": "光の弓使い",
    "desciption": "光の精霊と契約したエルフの弓使い。\nその矢は、敵を光で包み込む。\n森の守護者として、侵入者を決して許さない。",
    "release_at": "2026-06-11 00:00:00",
    "display_order": 22,
    "size": 1,
    "quest_type": 2,
    "quest_id": 1060505
  },
  {
    "id": 10822,
    "asset_id": "2012501",
    "group_no": 9,
    "item_no": 74,
    "priority_order": 1,
    "title": "闇の弓使い",
    "desciption": "闇の精霊と契約したエルフの弓使い。\nその矢は、邪悪な闇を纏い、敵を闇に葬る。\n森の守護者として、侵入者を決して許さない。",
    "release_at": "2026-06-11 00:00:00",
    "display_order": 23,
    "size": 1,
    "quest_type": 2,
    "quest_id": 1040505
  },
  {
    "id": 10823,
    "asset_id": "2012001",
    "group_no": 9,
    "item_no": 75,
    "priority_order": 1,
    "title": "空の弓使い",
    "desciption": "空を司るエルフの弓使い。\nその矢は、空気を切り裂き敵を貫く。\n森の守護者として、侵入者を決して許さない。",
    "release_at": "2026-06-11 00:00:00",
    "display_order": 24,
    "size": 1,
    "quest_type": 2,
    "quest_id": 1050503
  },
  {
    "id": 10824,
    "asset_id": "2013101",
    "group_no": 9,
    "item_no": 76,
    "priority_order": 1,
    "title": "炎の修道士",
    "desciption": "灼熱の炎を操る修道士。\nその手は、傷を癒し、生命力を燃え上がらせる。\n炎の力は、彼に治癒の奇跡をもたらす。",
    "release_at": "2026-06-11 00:00:00",
    "display_order": 25,
    "size": 1,
    "quest_type": 2,
    "quest_id": 1030503
  },
  {
    "id": 10825,
    "asset_id": "2013201",
    "group_no": 9,
    "item_no": 77,
    "priority_order": 1,
    "title": "水の修道士",
    "desciption": "水を操る修道士。\nその手は、傷を癒し、疲れた体を潤す。\n水は、彼に治癒の知恵を与える。",
    "release_at": "2026-06-11 00:00:00",
    "display_order": 26,
    "size": 1,
    "quest_type": 2,
    "quest_id": 1020406
  },
  {
    "id": 10826,
    "asset_id": "2013301",
    "group_no": 9,
    "item_no": 78,
    "priority_order": 1,
    "title": "地の修道士",
    "desciption": "大地の精霊を操る修道士。\nその手は、大地の恵みを与え、生命力を育む。\n大地の力は、彼に回復の滋養をもたらす。",
    "release_at": "2026-06-11 00:00:00",
    "display_order": 27,
    "size": 1,
    "quest_type": 2,
    "quest_id": 1010306
  },
  {
    "id": 10827,
    "asset_id": "2013401",
    "group_no": 9,
    "item_no": 79,
    "priority_order": 1,
    "title": "光の修道士",
    "desciption": "光を操る修道士。\nその手は、聖なる光を注ぎ、生命力を輝かせる。\n光の力は、彼に浄化の癒しをもたらす。",
    "release_at": "2026-06-11 00:00:00",
    "display_order": 28,
    "size": 1,
    "quest_type": 2,
    "quest_id": 1060505
  },
  {
    "id": 10828,
    "asset_id": "2013501",
    "group_no": 9,
    "item_no": 80,
    "priority_order": 1,
    "title": "闇の修道士",
    "desciption": "闇を操る修道士。\nその祈りは、死の淵から生命を引き戻し、傷を癒す。\n闇の力は、彼に禁断の治癒をもたらす。",
    "release_at": "2026-06-11 00:00:00",
    "display_order": 29,
    "size": 1,
    "quest_type": 2,
    "quest_id": 1040505
  },
  {
    "id": 10829,
    "asset_id": "2013001",
    "group_no": 9,
    "item_no": 81,
    "priority_order": 1,
    "title": "虚の修道士",
    "desciption": "虚無を操る修道士。\nその祈りは、生命を完全な状態へと回帰させる。\n虚の力は、彼に究極の再生をもたらす。",
    "release_at": "2026-06-11 00:00:00",
    "display_order": 30,
    "size": 1,
    "quest_type": 2,
    "quest_id": 1050503
  },
  {
    "id": 10900,
    "asset_id": "2014101",
    "group_no": 10,
    "item_no": 82,
    "priority_order": 1,
    "title": "ファイヤーマンイーター",
    "desciption": "燃え盛る花弁を持つ食人植物。\nその牙は鋭く獲物を逃さない。\n口から吐き出す炎は、すべてを焼き尽くす。",
    "release_at": "2026-06-11 00:00:00",
    "display_order": 1,
    "size": 3,
    "quest_type": 2,
    "quest_id": 1030503
  },
  {
    "id": 10901,
    "asset_id": "2014201",
    "group_no": 10,
    "item_no": 83,
    "priority_order": 1,
    "title": "アクアマンイーター",
    "desciption": "凍てつく花弁を持つ食人植物。\nその牙は鋭く獲物を逃さない。\n口から吐き出す冷気は、すべてを凍結させる。",
    "release_at": "2026-06-11 00:00:00",
    "display_order": 2,
    "size": 3,
    "quest_type": 2,
    "quest_id": 1020406
  },
  {
    "id": 10902,
    "asset_id": "2014301",
    "group_no": 10,
    "item_no": 84,
    "priority_order": 1,
    "title": "ガイアマンイーター",
    "desciption": "豊穣の花弁を持つ食人植物。\nその牙は鋭く獲物を逃さない。\n口から吐き出す胞子は、すべてを蝕む。",
    "release_at": "2026-06-11 00:00:00",
    "display_order": 3,
    "size": 3,
    "quest_type": 2,
    "quest_id": 1010306
  },
  {
    "id": 10903,
    "asset_id": "2014401",
    "group_no": 10,
    "item_no": 85,
    "priority_order": 1,
    "title": "ホーリーマンイーター",
    "desciption": "聖なる花弁を持つ食人植物。\nその牙は鋭く獲物を逃さない。\n口から吐き出す光は、すべてを盲目にする。",
    "release_at": "2026-06-11 00:00:00",
    "display_order": 4,
    "size": 3,
    "quest_type": 2,
    "quest_id": 1060505
  },
  {
    "id": 10904,
    "asset_id": "2014501",
    "group_no": 10,
    "item_no": 86,
    "priority_order": 1,
    "title": "シャドウマンイーター",
    "desciption": "呪われた花弁を持つ食人植物。\nその牙は鋭く獲物を逃さない。\n口から吐き出す瘴気は、すべてを腐敗させる。",
    "release_at": "2026-06-11 00:00:00",
    "display_order": 5,
    "size": 3,
    "quest_type": 2,
    "quest_id": 1040505
  },
  {
    "id": 10905,
    "asset_id": "2014001",
    "group_no": 10,
    "item_no": 87,
    "priority_order": 1,
    "title": "バドマンイーター",
    "desciption": "花弁が咲く前の食人植物。\nその牙は鋭く獲物を逃さない。\n口から吐き出す胞子は獲物を混乱に陥れる。",
    "release_at": "2026-06-11 00:00:00",
    "display_order": 6,
    "size": 3,
    "quest_type": 2,
    "quest_id": 1050503
  },
  {
    "id": 11000,
    "asset_id": "2015101",
    "group_no": 11,
    "item_no": 88,
    "priority_order": 1,
    "title": "フレイムミノタウロス",
    "desciption": "灼熱の斧を振るう、牛頭人身のモンスター。\nその獰猛な突進は炎の嵐を巻き起こし、\n戦場を焼き尽くす。",
    "release_at": "2026-06-11 00:00:00",
    "display_order": 1,
    "size": 3,
    "quest_type": 2,
    "quest_id": 1030503
  },
  {
    "id": 11001,
    "asset_id": "2015201",
    "group_no": 11,
    "item_no": 89,
    "priority_order": 1,
    "title": "マリンミノタウロス",
    "desciption": "巨大な錨を振り回す、牛頭人身のモンスター。\nその荒波のような攻撃はすべてを飲み込み、\n戦場を凍てつかせる。",
    "release_at": "2026-06-11 00:00:00",
    "display_order": 2,
    "size": 3,
    "quest_type": 2,
    "quest_id": 1020406
  },
  {
    "id": 11002,
    "asset_id": "2015301",
    "group_no": 11,
    "item_no": 90,
    "priority_order": 1,
    "title": "ガイアミノタウロス",
    "desciption": "重いこん棒を振り下ろす、牛頭人身のモンスター。\nその一撃は大地を揺るがし、\nすべてを粉砕する。",
    "release_at": "2026-06-11 00:00:00",
    "display_order": 3,
    "size": 3,
    "quest_type": 2,
    "quest_id": 1010306
  },
  {
    "id": 11003,
    "asset_id": "2015401",
    "group_no": 11,
    "item_no": 91,
    "priority_order": 1,
    "title": "ホーリーミノタウロス",
    "desciption": "聖なる剣を掲げる、牛頭人身のモンスター。\nその光に満ちた刃は邪悪を断ち切り、\nすべてを浄化する。",
    "release_at": "2026-06-11 00:00:00",
    "display_order": 4,
    "size": 3,
    "quest_type": 2,
    "quest_id": 1060505
  },
  {
    "id": 11004,
    "asset_id": "2015501",
    "group_no": 11,
    "item_no": 92,
    "priority_order": 1,
    "title": "シャドウミノタウロス",
    "desciption": "巨大ハンマーを叩きつける牛頭人身のモンスター。\nその一撃は影をも打ち砕き、\nすべてを闇に染める。",
    "release_at": "2026-06-11 00:00:00",
    "display_order": 5,
    "size": 3,
    "quest_type": 2,
    "quest_id": 1040505
  },
  {
    "id": 11005,
    "asset_id": "2015001",
    "group_no": 11,
    "item_no": 93,
    "priority_order": 1,
    "title": "アイアンミノタウロス",
    "desciption": "強靭な鉄槌を振るう、牛頭人身のモンスター。\nその豪腕は、いかなる盾も打ち砕き、\n容赦なく敵を粉砕する。",
    "release_at": "2026-06-11 00:00:00",
    "display_order": 6,
    "size": 3,
    "quest_type": 2,
    "quest_id": 1050503
  },
  {
    "id": 11100,
    "asset_id": "2016101",
    "group_no": 12,
    "item_no": 95,
    "priority_order": 1,
    "title": "フレイムバジリスク",
    "desciption": "炎の鱗を持つ大トカゲ。\n口から灼熱の溶岩を吐き、戦場を灰に変える。\n近づく者を寄せ付けない炎の支配者。",
    "release_at": "2026-06-11 00:00:00",
    "display_order": 1,
    "size": 3,
    "quest_type": 2,
    "quest_id": 1030503
  },
  {
    "id": 11101,
    "asset_id": "2016201",
    "group_no": 12,
    "item_no": 96,
    "priority_order": 1,
    "title": "アイスバジリスク",
    "desciption": "氷の鱗を持つ大トカゲ。\n口から極寒の氷結液を吐き相手を凍てつかせる。\n冷気を纏う鱗は触れるだけで霜を刻む。",
    "release_at": "2026-06-11 00:00:00",
    "display_order": 2,
    "size": 3,
    "quest_type": 2,
    "quest_id": 1020406
  },
  {
    "id": 11102,
    "asset_id": "2016301",
    "group_no": 12,
    "item_no": 97,
    "priority_order": 1,
    "title": "ロックバジリスク",
    "desciption": "岩の鱗を持つ大トカゲ。\n口から泥を吐き、敵を土の下に埋める。\nその姿は、大地の怒りを体現したかのよう。",
    "release_at": "2026-06-11 00:00:00",
    "display_order": 3,
    "size": 3,
    "quest_type": 2,
    "quest_id": 1010306
  },
  {
    "id": 11103,
    "asset_id": "2016401",
    "group_no": 12,
    "item_no": 98,
    "priority_order": 1,
    "title": "ライトバジリスク",
    "desciption": "輝く鱗を持つ大トカゲ。\n眩い光を口から放ち、視界を奪い焼き尽くす。\n聖なる輝きを纏うが、その本性は冷酷な捕食者。",
    "release_at": "2026-06-11 00:00:00",
    "display_order": 4,
    "size": 3,
    "quest_type": 2,
    "quest_id": 1060505
  },
  {
    "id": 11104,
    "asset_id": "2016501",
    "group_no": 12,
    "item_no": 99,
    "priority_order": 1,
    "title": "ダークバジリスク",
    "desciption": "闇の鱗を持つ大トカゲ。\n口から闇を吐き、相手を永遠の暗闇に閉じ込める。\n光を吸い込む鱗は不気味に蠢き、絶望の淵へと誘う。",
    "release_at": "2026-06-11 00:00:00",
    "display_order": 5,
    "size": 3,
    "quest_type": 2,
    "quest_id": 1040505
  },
  {
    "id": 11105,
    "asset_id": "2016001",
    "group_no": 12,
    "item_no": 100,
    "priority_order": 1,
    "title": "アイアンバジリスク",
    "desciption": "鉄の鱗を持つ大トカゲ。\n口から透明な液体を放ち、毒牙にかける。\n無機質な鱗の下に潜むのは、感情なき殺戮の本能。",
    "release_at": "2026-06-11 00:00:00",
    "display_order": 6,
    "size": 3,
    "quest_type": 2,
    "quest_id": 1050503
  },
  {
    "id": 11200,
    "asset_id": "2017401",
    "group_no": 13,
    "item_no": 101,
    "priority_order": 1,
    "title": "大穴の番人 アーマーナイト",
    "desciption": "呪われし力を持つ鋼鉄の守護者。\nその大剣は、侵入者を断ち切り、\nその鎧は、決して砕けることはない。",
    "release_at": "2026-06-11 00:00:00",
    "display_order": 1,
    "size": 4,
    "quest_type": 2,
    "quest_id": 1010306
  },
  {
    "id": 11201,
    "asset_id": "2017501",
    "group_no": 13,
    "item_no": 102,
    "priority_order": 1,
    "title": "威光の番人 ブライトアーマー",
    "desciption": "神秘な力を持つ鋼鉄の守護者。\nその大剣は、侵入者を断ち切り、\nその鎧は、決して砕けることはない。",
    "release_at": "2026-06-11 00:00:00",
    "display_order": 2,
    "size": 4,
    "quest_type": 2,
    "quest_id": 1060505
  },
  {
    "id": 11300,
    "asset_id": "2018101",
    "group_no": 14,
    "item_no": 104,
    "priority_order": 1,
    "title": "フレイムドラゴン",
    "desciption": "炎の鱗を持つ翼竜。\n口から灼熱のブレスを吐き、大地を焦がす。\nその咆哮は空を赤く染める。炎の守護者",
    "release_at": "2026-06-11 00:00:00",
    "display_order": 1,
    "size": 4,
    "quest_type": 2,
    "quest_id": 1030503
  },
  {
    "id": 11301,
    "asset_id": "2018201",
    "group_no": 14,
    "item_no": 105,
    "priority_order": 1,
    "title": "アイスドラゴン",
    "desciption": "氷の鱗を持つ翼竜。\n口から凍てつくブレスを吐き、万物を氷結させる。\nその翼が舞えば吹雪が荒れ狂う。氷河の守護者。",
    "release_at": "2026-06-11 00:00:00",
    "display_order": 2,
    "size": 4,
    "quest_type": 2,
    "quest_id": 1020406
  },
  {
    "id": 11400,
    "asset_id": "2019301",
    "group_no": 15,
    "item_no": 106,
    "priority_order": 1,
    "title": "アースホーン・キマイラ",
    "desciption": "巨大な合成魔獣。岩山のような固い角を持つ。\n一突きで大地を揺るがし、\n対峙者を奈落の底へと突き落とす。",
    "release_at": "2026-06-11 00:00:00",
    "display_order": 1,
    "size": 4,
    "quest_type": 2,
    "quest_id": 1010306
  },
  {
    "id": 11401,
    "asset_id": "2019001",
    "group_no": 15,
    "item_no": 107,
    "priority_order": 1,
    "title": "メタルホーン・キマイラ",
    "desciption": "異世界の技術で造られらた合成魔獣。\nその角の硬度はダイヤモンドに匹敵し、\nあらゆるものを貫通する。",
    "release_at": "2026-06-11 00:00:00",
    "display_order": 2,
    "size": 4,
    "quest_type": 2,
    "quest_id": 1050503
  },
  {
    "id": 11500,
    "asset_id": "2028101",
    "group_no": 16,
    "item_no": 108,
    "priority_order": 1,
    "title": "炎の盗賊",
    "desciption": "火属性の扱いに長けた盗賊。\nいかなる環境下においても獲物を攻撃する\n厄介な情熱を持っている。",
    "release_at": "2026-06-11 00:00:00",
    "display_order": 1,
    "size": 1,
    "quest_type": 2,
    "quest_id": 1030503
  },
  {
    "id": 11501,
    "asset_id": "2028201",
    "group_no": 16,
    "item_no": 109,
    "priority_order": 1,
    "title": "水の盗賊",
    "desciption": "水属性の扱いに長けた盗賊。\nいかなる環境下においても獲物を逃さない\n厄介な冷静さを持っている。",
    "release_at": "2026-06-11 00:00:00",
    "display_order": 2,
    "size": 1,
    "quest_type": 2,
    "quest_id": 1020406
  },
  {
    "id": 11502,
    "asset_id": "2028301",
    "group_no": 16,
    "item_no": 110,
    "priority_order": 1,
    "title": "地の盗賊",
    "desciption": "土属性の扱いに長けた盗賊。\nいかなる環境下においても獲物を追い続ける\n厄介な根気を持っている。",
    "release_at": "2026-06-11 00:00:00",
    "display_order": 3,
    "size": 1,
    "quest_type": 2,
    "quest_id": 1010306
  },
  {
    "id": 11503,
    "asset_id": "2028401",
    "group_no": 16,
    "item_no": 111,
    "priority_order": 1,
    "title": "光の盗賊",
    "desciption": "光属性の扱いに長けた盗賊。\nいかなる環境下においても獲物を諦めない\n厄介なポジティブさを持っている。",
    "release_at": "2026-06-11 00:00:00",
    "display_order": 4,
    "size": 1,
    "quest_type": 2,
    "quest_id": 1060505
  },
  {
    "id": 11504,
    "asset_id": "2028501",
    "group_no": 16,
    "item_no": 112,
    "priority_order": 1,
    "title": "闇の盗賊",
    "desciption": "闇属性の扱いに長けた盗賊。\nいかなる環境下においても獲物をいたぶる\n厄介な陰湿さを持っている。",
    "release_at": "2026-06-11 00:00:00",
    "display_order": 5,
    "size": 1,
    "quest_type": 2,
    "quest_id": 1040505
  },
  {
    "id": 11505,
    "asset_id": "2028001",
    "group_no": 16,
    "item_no": 113,
    "priority_order": 1,
    "title": "鉄の盗賊",
    "desciption": "武器の扱いに長けた盗賊。\nいかなる環境下においても獲物を無心で追う\n厄介な集中力を持っている。",
    "release_at": "2026-06-11 00:00:00",
    "display_order": 6,
    "size": 1,
    "quest_type": 2,
    "quest_id": 1050503
  },
  {
    "id": 11506,
    "asset_id": "2029101",
    "group_no": 16,
    "item_no": 114,
    "priority_order": 1,
    "title": "炎の盗賊頭",
    "desciption": "火属性の扱いに非常に長けた盗賊のリーダー。\nあらゆる状況下で常に獲物を攻撃する\n執拗なまでの情熱を持っている。",
    "release_at": "2026-06-11 00:00:00",
    "display_order": 7,
    "size": 1,
    "quest_type": 2,
    "quest_id": 1030503
  },
  {
    "id": 11507,
    "asset_id": "2029201",
    "group_no": 16,
    "item_no": 115,
    "priority_order": 1,
    "title": "水の盗賊頭",
    "desciption": "水属性の扱いに非常に長けた盗賊のリーダー。\nあらゆる状況下で常に獲物を逃がさない\n執拗なまでの冷静さを持っている。",
    "release_at": "2026-06-11 00:00:00",
    "display_order": 8,
    "size": 1,
    "quest_type": 2,
    "quest_id": 1020406
  },
  {
    "id": 11508,
    "asset_id": "2029301",
    "group_no": 16,
    "item_no": 116,
    "priority_order": 1,
    "title": "地の盗賊頭",
    "desciption": "土属性の扱いに非常に長けた盗賊のリーダー。\nあらゆる状況下で常に獲物を追い続ける\n執拗なまでの根気を持っている。",
    "release_at": "2026-06-11 00:00:00",
    "display_order": 9,
    "size": 1,
    "quest_type": 2,
    "quest_id": 1010306
  },
  {
    "id": 11509,
    "asset_id": "2029401",
    "group_no": 16,
    "item_no": 117,
    "priority_order": 1,
    "title": "光の盗賊頭",
    "desciption": "光属性の扱いに非常に長けた盗賊のリーダー。\nあらゆる状況下で常に獲物をあきらめない\n執拗なまでのポジティブさを持っている。",
    "release_at": "2026-06-11 00:00:00",
    "display_order": 10,
    "size": 1,
    "quest_type": 2,
    "quest_id": 1060505
  },
  {
    "id": 11510,
    "asset_id": "2029501",
    "group_no": 16,
    "item_no": 118,
    "priority_order": 1,
    "title": "闇の盗賊頭",
    "desciption": "闇属性の扱いに非常に長けた盗賊のリーダー。\nあらゆる状況下で常に獲物をいたぶる\n執拗なまでの陰湿さを持っている。",
    "release_at": "2026-06-11 00:00:00",
    "display_order": 11,
    "size": 1,
    "quest_type": 2,
    "quest_id": 1040505
  },
  {
    "id": 11511,
    "asset_id": "2029001",
    "group_no": 16,
    "item_no": 119,
    "priority_order": 1,
    "title": "鋼の盗賊頭",
    "desciption": "武器の扱いに非常に長けた盗賊のリーダー。\nあらゆる状況下で常に獲物を無心で追う\n執拗なまでの集中力を持っている。",
    "release_at": "2026-06-11 00:00:00",
    "display_order": 12,
    "size": 1,
    "quest_type": 2,
    "quest_id": 1050503
  },
  {
    "id": 11600,
    "asset_id": "2030101",
    "group_no": 17,
    "item_no": 120,
    "priority_order": 1,
    "title": "炎のエレメンタル",
    "desciption": "燃え盛る炎の元素が意志を持ち具現化した姿。\n厄災による影響か非常に好戦的で近くにいる\n人類を狙い、焼き尽くそうとしてくる。",
    "release_at": "2026-06-11 00:00:00",
    "display_order": 1,
    "size": 4,
    "quest_type": 2,
    "quest_id": 1030503
  },
  {
    "id": 11601,
    "asset_id": "2030201",
    "group_no": 17,
    "item_no": 121,
    "priority_order": 1,
    "title": "水のエレメンタル",
    "desciption": "流れ滴る水の元素が意志を持ち具現化した姿。\n厄災による影響か非常に好戦的で近くにいる\n人類を狙い、押し流そうとしてくる。",
    "release_at": "2026-06-11 00:00:00",
    "display_order": 2,
    "size": 4,
    "quest_type": 2,
    "quest_id": 1020406
  },
  {
    "id": 11602,
    "asset_id": "2030301",
    "group_no": 17,
    "item_no": 122,
    "priority_order": 1,
    "title": "地のエレメンタル",
    "desciption": "壮大なる大地の元素が意志を持ち具現化した姿。\n厄災による影響か非常に好戦的で近くにいる\n人類を狙い、押しつぶそうとしてくる。",
    "release_at": "2026-06-11 00:00:00",
    "display_order": 3,
    "size": 4,
    "quest_type": 2,
    "quest_id": 1010306
  },
  {
    "id": 11603,
    "asset_id": "2030401",
    "group_no": 17,
    "item_no": 123,
    "priority_order": 1,
    "title": "光のエレメンタル",
    "desciption": "万物を照らす光の元素が意志を持ち具現化した姿。\n厄災による影響か非常に好戦的で近くにいる\n人類を狙い、閃光で貫こうとしてくる。",
    "release_at": "2026-06-11 00:00:00",
    "display_order": 4,
    "size": 4,
    "quest_type": 2,
    "quest_id": 1060505
  },
  {
    "id": 11604,
    "asset_id": "2030501",
    "group_no": 17,
    "item_no": 124,
    "priority_order": 1,
    "title": "闇のエレメンタル",
    "desciption": "万物を飲み込む闇の元素が意志を持ち具現化した姿。\n厄災による影響か非常に好戦的で近くにいる\n人類を狙い、全ての輝きを奪おうとしてくる。",
    "release_at": "2026-06-11 00:00:00",
    "display_order": 5,
    "size": 4,
    "quest_type": 2,
    "quest_id": 1040505
  },
  {
    "id": 11605,
    "asset_id": "2030001",
    "group_no": 17,
    "item_no": 125,
    "priority_order": 1,
    "title": "空のエレメンタル",
    "desciption": "虚ろなる無の元素が意志を持ち具現化した姿。\n厄災による影響か非常に好戦的で近くにいる\n人類を狙い、虚空へと引きずり込もうとしてくる。",
    "release_at": "2026-06-11 00:00:00",
    "display_order": 6,
    "size": 4,
    "quest_type": 2,
    "quest_id": 1050503
  }
]