[
  {
    "id": 1,
    "m_feature_lock_id": 1,
    "condition_type": 2,
    "condition_param": 101030301,
    "condition_text": "1章8話「建てました。」クリアで解放"
  },
  {
    "id": 2,
    "m_feature_lock_id": 2,
    "condition_type": 1,
    "condition_param": 1010101,
    "condition_text": "1章1話「こんな部隊、最悪よ～！！！！」クリアで解放"
  },
  {
    "id": 3,
    "m_feature_lock_id": 3,
    "condition_type": 1,
    "condition_param": 1010306,
    "condition_text": "1章クリアで解放"
  },
  {
    "id": 4,
    "m_feature_lock_id": 4,
    "condition_type": 1,
    "condition_param": 1030503,
    "condition_text": "3章クリアで解放"
  },
  {
    "id": 5,
    "m_feature_lock_id": 5,
    "condition_type": 1,
    "condition_param": 1060505,
    "condition_text": "6章クリアで解放"
  },
  {
    "id": 6,
    "m_feature_lock_id": 6,
    "condition_type": 1,
    "condition_param": 1010202,
    "condition_text": "1章3話「予兆？」クリアで解放"
  },
  {
    "id": 7,
    "m_feature_lock_id": 7,
    "condition_type": 3,
    "condition_param": 3,
    "condition_text": "交流でスタッフ登録3人以上で解放"
  },
  {
    "id": 8,
    "m_feature_lock_id": 8,
    "condition_type": 2,
    "condition_param": 101010102,
    "condition_text": "1章1話「こんな部隊、最悪よ～！！！！」クリアで解放"
  },
  {
    "id": 1001,
    "m_feature_lock_id": 1001,
    "condition_type": 1,
    "condition_param": 1010101,
    "condition_text": "1章1話「こんな部隊、最悪よ～！！！！」クリアで解放"
  },
  {
    "id": 1002,
    "m_feature_lock_id": 1002,
    "condition_type": 1,
    "condition_param": 1060505,
    "condition_text": "6章クリアで解放"
  },
  {
    "id": 1003,
    "m_feature_lock_id": 1003,
    "condition_type": 1,
    "condition_param": 1010101,
    "condition_text": "1章1話「こんな部隊、最悪よ～！！！！」クリアで解放"
  },
  {
    "id": 1004,
    "m_feature_lock_id": 1004,
    "condition_type": 1,
    "condition_param": 1010101,
    "condition_text": "1章1話「こんな部隊、最悪よ～！！！！」クリアで解放"
  },
  {
    "id": 1005,
    "m_feature_lock_id": 1005,
    "condition_type": 1,
    "condition_param": 1010101,
    "condition_text": "1章1話「こんな部隊、最悪よ～！！！！」クリアで解放"
  },
  {
    "id": 1006,
    "m_feature_lock_id": 1006,
    "condition_type": 1,
    "condition_param": 1010101,
    "condition_text": "1章1話「こんな部隊、最悪よ～！！！！」クリアで解放"
  },
  {
    "id": 1007,
    "m_feature_lock_id": 1007,
    "condition_type": 1,
    "condition_param": 1030503,
    "condition_text": "3章クリアで解放"
  },
  {
    "id": 1008,
    "m_feature_lock_id": 1008,
    "condition_type": 1,
    "condition_param": 1010101,
    "condition_text": "1章1話「こんな部隊、最悪よ～！！！！」クリアで解放"
  }
]